cognitive_sdk_plus/__init__.py
cognitive_sdk_plus/core/__init__.py
cognitive_sdk_plus/core/metadata_responder.py
cognitive_sdk_plus/core/orcustrator.py
cognitive_sdk_plus/core/proxy.py
cognitive_sdk_plus/core/publisher.py
cognitive_sdk_plus/core/subscriber.py
cognitive_sdk_plus/core/subscriber_manager.py
cognitive_sdk_plus/core_plus/__init__.py
cognitive_sdk_plus/core_plus/uploader/__init__.py
cognitive_sdk_plus/core_plus/uploader/rabbitmq_manager.py
cognitive_sdk_plus/core_plus/uploader/rabbitmq_publisher.py
cognitive_sdk_plus/core_plus/uploader/uploader_manager.py
cognitive_sdk_plus/devices/__init__.py
cognitive_sdk_plus/devices/device.py
cognitive_sdk_plus/devices/device_manager.py
cognitive_sdk_plus/devices/subdevice.py
cognitive_sdk_plus/devices/middlewares/__init__.py
cognitive_sdk_plus/devices/middlewares/brainflow.py
cognitive_sdk_plus/devices/middlewares/synthetic.py
cognitive_sdk_plus/presets/Muse-2.json
cognitive_sdk_plus/presets/Muse-S.json
cognitive_sdk_plus/presets/OpenBCI-daisy.json
cognitive_sdk_plus/presets/Synthetic.json
cognitive_sdk_plus/presets/__init__.py
cognitive_sdk_plus/utils/__init__.py
cognitive_sdk_plus/utils/helpers.py
cognitive_sdk_plus/utils/logger.py
cognitive_sdk_plus/utils/ports.py
cognitive_sdk_plus/utils/shared_state.py
cognitive_sdk_plus-1.0.0.post2.dist-info/METADATA
cognitive_sdk_plus-1.0.0.post2.dist-info/WHEEL
cognitive_sdk_plus-1.0.0.post2.dist-info/top_level.txt
cognitive_sdk_plus-1.0.0.post2.dist-info/RECORD
