Metadata-Version: 2.4
Name: cognitive_sdk_plus
Version: 1.0.0.post2
Summary: Cognitive SDK Plus
Author: Turan Abdullah
Author-email: abdullah@habs.ai
Requires-Python: >=3.10
Requires-Dist: loguru
Requires-Dist: zmq==0.0.0
Requires-Dist: pyyaml
Requires-Dist: numpy==2.2.4
Requires-Dist: brainflow==5.16.0
Requires-Dist: httpx==0.28.1
Requires-Dist: pika==1.3.2
Requires-Dist: pandas
Requires-Dist: requests
Dynamic: author
Dynamic: author-email
Dynamic: requires-dist
Dynamic: requires-python
Dynamic: summary
